lucipy/__init__.py
lucipy/circuits.py
lucipy/detect.py
lucipy/simulator.py
lucipy/synchc.py
lucipy-1.7.2.dist-info/licenses/LICENSE.md
lucipy-1.7.2.dist-info/METADATA
lucipy-1.7.2.dist-info/WHEEL
lucipy-1.7.2.dist-info/top_level.txt
lucipy-1.7.2.dist-info/RECORD
