Metadata-Version: 2.4
Name: lucipy
Version: 1.7.2
Summary: Client library for the LUCIDAC analog digital hybrid computer
Author-email: The Analog Geeks <pybrid-code@anabrid.com>
License: SPDX-License-Identifier: MIT OR GPL-2.0-or-later
Project-URL: Homepage, https://anabrid.com/
Project-URL: Documentation, https://anabrid.dev/docs/lucipy/
Project-URL: Repository, https://github.com/anabrid/lucipy
Classifier: Development Status :: 5 - Production/Stable
Classifier: Environment :: Console
Classifier: Intended Audience :: Developers
Classifier: Intended Audience :: Science/Research
Classifier: Intended Audience :: End Users/Desktop
Classifier: Topic :: Communications
Classifier: Topic :: Scientific/Engineering :: Interface Engine/Protocol Translator
Classifier: Topic :: Software Development :: Embedded Systems
Classifier: Topic :: Terminals :: Serial
Classifier: Operating System :: POSIX
Requires-Python: >=3.8
License-File: LICENSE.md
Provides-Extra: serial
Requires-Dist: pyserial>=3.5; extra == "serial"
Provides-Extra: detection
Requires-Dist: zeroconf>=0.63.0; extra == "detection"
Dynamic: license-file
